Metadata-Version: 2.2
Name: csi_analysis
Version: 0.5.0
Summary: CSI-Cancer analysis pipeline templates.
Author-email: Brian Zhang <8885230+brianjzhang@users.noreply.github.com>
Requires-Python: >=3.11
License-File: LICENSE
Requires-Dist: csi_images>=3.0.0
Requires-Dist: numpy
Requires-Dist: pandas
Requires-Dist: loguru
Requires-Dist: tqdm
Provides-Extra: images
Requires-Dist: csi_images[imageio]>=3.0.0; extra == "images"
Requires-Dist: scikit-image; extra == "images"
Requires-Dist: opencv-python; extra == "images"
Provides-Extra: cpu-ml
Requires-Dist: torch; extra == "cpu-ml"
Requires-Dist: torchvision; extra == "cpu-ml"
Requires-Dist: torchsummary; extra == "cpu-ml"
Requires-Dist: scikit-learn; extra == "cpu-ml"
Provides-Extra: gpu-ml
Requires-Dist: torch; extra == "gpu-ml"
Requires-Dist: torchvision; extra == "gpu-ml"
Requires-Dist: torchsummary; extra == "gpu-ml"
Requires-Dist: cuml; extra == "gpu-ml"
Provides-Extra: cellpose
Requires-Dist: cellpose; extra == "cellpose"
Provides-Extra: training
Requires-Dist: torch; extra == "training"
Requires-Dist: torchvision; extra == "training"
Requires-Dist: torchsummary; extra == "training"
Provides-Extra: dev
Requires-Dist: pdoc; extra == "dev"
Requires-Dist: pytest; extra == "dev"
Requires-Dist: hatchling; extra == "dev"
Requires-Dist: build; extra == "dev"
Requires-Dist: twine; extra == "dev"
Provides-Extra: all
Requires-Dist: csi_analysis[images]; extra == "all"
Requires-Dist: csi_analysis[cpu_ml]; extra == "all"
Requires-Dist: csi_analysis[gpu_ml]; extra == "all"
Requires-Dist: csi_analysis[cellpose]; extra == "all"
Requires-Dist: csi_analysis[dev]; extra == "all"
